metascout/__init__.py
metascout/__main__.py
metascout/cli.py
metascout/analyzers/__init__.py
metascout/analyzers/audio.py
metascout/analyzers/base.py
metascout/analyzers/document.py
metascout/analyzers/executable.py
metascout/analyzers/generic.py
metascout/analyzers/image.py
metascout/analyzers/pattern.py
metascout/analyzers/video.py
metascout/config/__init__.py
metascout/config/constants.py
metascout/config/dependencies.py
metascout/core/__init__.py
metascout/core/models.py
metascout/core/processor.py
metascout/core/utils.py
metascout/extractors/__init__.py
metascout/extractors/audio.py
metascout/extractors/base.py
metascout/extractors/document.py
metascout/extractors/executable.py
metascout/extractors/generic.py
metascout/extractors/image.py
metascout/extractors/video.py
metascout/operations/__init__.py
metascout/operations/analyze.py
metascout/operations/batch.py
metascout/operations/compare.py
metascout/operations/redact.py
metascout/reporters/__init__.py
metascout/reporters/base.py
metascout/reporters/csv.py
metascout/reporters/html.py
metascout/reporters/json.py
metascout/reporters/text.py
metascout-1.0.0.dist-info/METADATA
metascout-1.0.0.dist-info/WHEEL
metascout-1.0.0.dist-info/entry_points.txt
metascout-1.0.0.dist-info/top_level.txt
metascout-1.0.0.dist-info/RECORD
