Metadata-Version: 2.4
Name: metascout
Version: 1.0.0
Summary: Advanced file metadata analysis and security tool
Home-page: https://github.com/ParleSec/metascout
Author: Mason Parle
Author-email: mason@masonparle.com
Project-URL: Bug Tracker, https://github.com/ParleSec/metascout/issues
Project-URL: Documentation, https://github.com/ParleSec/metascout#readme
Project-URL: Source Code, https://github.com/ParleSec/metascout
Keywords: metadata,security,privacy,analysis,exif,pii
Classifier: Programming Language :: Python :: 3
Classifier: Programming Language :: Python :: 3.8
Classifier: Programming Language :: Python :: 3.9
Classifier: Programming Language :: Python :: 3.10
Classifier: License :: OSI Approved :: MIT License
Classifier: Operating System :: OS Independent
Classifier: Topic :: Security
Classifier: Topic :: Security :: Cryptography
Classifier: Topic :: System :: Systems Administration
Classifier: Intended Audience :: Information Technology
Classifier: Intended Audience :: System Administrators
Classifier: Development Status :: 5 - Production/Stable
Classifier: Natural Language :: English
Requires-Python: >=3.8
Requires-Dist: pillow>=9.0.0
Requires-Dist: PyPDF2>=2.0.0
Requires-Dist: python-magic>=0.4.24; platform_system != "Windows"
Requires-Dist: python-magic-bin>=0.4.14; platform_system == "Windows"
Requires-Dist: mutagen>=1.45.0
Requires-Dist: colorama>=0.4.4
Requires-Dist: tabulate>=0.8.9
Requires-Dist: tqdm>=4.62.0
Requires-Dist: exifread>=2.3.2
Requires-Dist: cryptography>=35.0.0
Provides-Extra: full
Requires-Dist: python-docx>=0.8.11; extra == "full"
Requires-Dist: openpyxl>=3.0.7; extra == "full"
Requires-Dist: olefile>=0.46; extra == "full"
Requires-Dist: pefile>=2021.5.24; platform_system == "Windows" and extra == "full"
Requires-Dist: pyelftools>=0.27; platform_system != "Windows" and extra == "full"
Requires-Dist: macholib>=1.15.2; platform_system == "Darwin" and extra == "full"
Requires-Dist: yara-python>=4.1.0; extra == "full"
Requires-Dist: ssdeep>=3.4; extra == "full"
Provides-Extra: document
Requires-Dist: python-docx>=0.8.11; extra == "document"
Requires-Dist: openpyxl>=3.0.7; extra == "document"
Requires-Dist: olefile>=0.46; extra == "document"
Provides-Extra: executable
Requires-Dist: pefile>=2021.5.24; platform_system == "Windows" and extra == "executable"
Requires-Dist: pyelftools>=0.27; platform_system != "Windows" and extra == "executable"
Requires-Dist: macholib>=1.15.2; platform_system == "Darwin" and extra == "executable"
Provides-Extra: security
Requires-Dist: yara-python>=4.1.0; extra == "security"
Requires-Dist: ssdeep>=3.4; extra == "security"
Dynamic: author
Dynamic: author-email
Dynamic: classifier
Dynamic: description
Dynamic: description-content-type
Dynamic: home-page
Dynamic: keywords
Dynamic: project-url
Dynamic: provides-extra
Dynamic: requires-dist
Dynamic: requires-python
Dynamic: summary
